{
    "display": {
        "frame": "goal",
        "icon": {
            "item": "minecraft:milk_bucket"
        },
        "show_toast": false,
        "announce_to_chat": false,
        "hidden": true,
        "title": "Shelly Flavor",
        "background": "minecraft:milk_bucket",
        "description": "moo"
    },
    "rewards": {},
    "requirements": [
        [
            "turtlecrit"
        ]
    ],
    "criteria": {
        "turtlecrit": {
            "trigger": "minecraft:consume_item",
            "conditions": {
                "item": {
                    "item": "minecraft:milk_bucket",
                    "nbt": "{tag:cowturtle}"
                }
            }
        }
    }
}